mcubes/version.py
mcubes/exporter.py
mcubes/__init__.py
mcubes/numpy_smoothing.py
mcubes/_mcubes.cpython-312-darwin.so
mcubes/smoothing.py
PyMCubes-0.1.6.dist-info/RECORD
PyMCubes-0.1.6.dist-info/LICENSE
PyMCubes-0.1.6.dist-info/WHEEL
PyMCubes-0.1.6.dist-info/top_level.txt
PyMCubes-0.1.6.dist-info/METADATA
